scheptk/__init__.py
scheptk/scheptk.old.py
scheptk/scheptk.py
scheptk/util.py
scheptk-0.1.3.dist-info/LICENSE
scheptk-0.1.3.dist-info/METADATA
scheptk-0.1.3.dist-info/WHEEL
scheptk-0.1.3.dist-info/top_level.txt
scheptk-0.1.3.dist-info/RECORD
