Metadata-Version: 2.1
Name: scheptk
Version: 0.1.3
Summary: Python scheduling package
Home-page: https://github.com/framinan/scheptk
Author: Jose M Framinan
Author-email: framinan@us.es
Classifier: Programming Language :: Python :: 3.7
Classifier: License :: OSI Approved :: GNU General Public License v3 (GPLv3)
License-File: LICENSE
Requires-Dist: ipython (>=6)
Requires-Dist: nbformat (>=4)
Requires-Dist: nbconvert (>=5)
Requires-Dist: requests (>=2)
